Workbook
Name Cleaned_Data: Cleaned_Data!$A$1:$T$1081
Name EcommerceData: Cleaned_Data!$A$2:$Y$1051
Name Slicer_Order_Year: #N/A
Name Slicer_Region: #N/A
Name Slicer_Category: #N/A
Name Slicer_Payment_Method: #N/A

Sheet Cleaned_Data
A1: Order_ID | B1: Order_Date | C1: Order_Year | D1: Order_Month_No | E1: Order_Month | F1: Ship_Date | G1: Customer_ID | H1: Customer_Name | I1: Segment | J1: Country | K1: State | L1: City | M1: Region | N1: Product_ID | O1: Category | P1: Sub_Category | Q1: Product_Name | R1: Sales | S1: Quantity | T1: Discount | U1: Discount_Category | V1: Profit | W1: Profit Margin | X1: Shipping_Cost | Y1: Payment_Method | Z1: Order_Size
A2: ORD-10971 | B2: 45381 | C2: =YEAR(B2) -> 2024 | D2: =MONTH(B2) -> 3 | E2: =TEXT(B2,"mmmm") -> March | F2: 45383 | G2: CUST-7246 | H2: David Verma | I2: Home Office | J2: India | K2: Louisiana | L2: New Orleans | M2: South | N2: PROD-0041 | O2: Furniture | P2: Beds | Q2: IKEA MALM Bed Frame | R2: 898 | S2: 2 | T2: 0 | U2: =IF(T2=0,"No Discount",IF(T2<=0.1,"Low",IF(T2<=0.2,"Medium","High"))) -> No Discount | V2: 185.07 | W2: =V2/R2 -> 0.20609131 | X2: 41.63 | Y2: PayPal | Z2: =IF(R2<500,"Small",IF(R2<=2000,"Medium","Large")) -> Medium
A3: ORD-10176 | B3: 45138 | C3: =YEAR(B3) -> 2023 | D3: =MONTH(B3) -> 7 | E3: =TEXT(B3,"mmmm") -> July | F3: 45145 | G3: CUST-8264 | H3: Matthew Garcia | I3: Corporate | J3: United States | K3: Illinois | L3: Naperville | M3: Central | N3: PROD-0057 | O3: Clothing | P3: Women's Apparel | Q3: Anthropologie Blouse | R3: 268.6 | S3: 4 | T3: 0.15 | U3: =IF(T3=0,"No Discount",IF(T3<=0.1,"Low",IF(T3<=0.2,"Medium","High"))) -> Medium | V3: 45.37 | W3: =V3/R3 -> 0.16891288 | X3: 27.83 | Y3: UPI | Z3: =IF(R3<500,"Small",IF(R3<=2000,"Medium","Large")) -> Small
A4: ORD-10155 | B4: 44296 | C4: =YEAR(B4) -> 2021 | D4: =MONTH(B4) -> 4 | E4: =TEXT(B4,"mmmm") -> April | F4: 44301 | G4: CUST-9920 | H4: Maria Liu | I4: Consumer | J4: United States | K4: North Carolina | L4: Raleigh | M4: East | N4: PROD-0067 | O4: Clothing | P4: Sportswear | Q4: New Balance 990v5 | R4: 139.2 | S4: 1 | T4: 0.2 | U4: =IF(T4=0,"No Discount",IF(T4<=0.1,"Low",IF(T4<=0.2,"Medium","High"))) -> Medium | V4: -23.68 | W4: =V4/R4 -> -0.17011494 | X4: 41.83 | Y4: Wallet | Z4: =IF(R4<500,"Small",IF(R4<=2000,"Medium","Large")) -> Small
A5: ORD-10806 | B5: 44071 | C5: =YEAR(B5) -> 2020 | D5: =MONTH(B5) -> 8 | E5: =TEXT(B5,"mmmm") -> August | F5: 44077 | G5: CUST-8800 | H5: Maria Martinez | I5: Corporate | J5: United States | K5: Louisiana | L5: New Orleans | M5: South | N5: PROD-0002 | O5: Electronics | P5: Smartphones | Q5: Samsung Galaxy S24 | R5: 1278.4 | S5: 2 | T5: 0.2 | U5: =IF(T5=0,"No Discount",IF(T5<=0.1,"Low",IF(T5<=0.2,"Medium","High"))) -> Medium | V5: -113.67 | W5: =V5/R5 -> -0.088915832 | X5: 37.99 | Y5: Cash on Delivery | Z5: =IF(R5<500,"Small",IF(R5<=2000,"Medium","Large")) -> Medium
A6: ORD-10470 | B6: 44659 | C6: =YEAR(B6) -> 2022 | D6: =MONTH(B6) -> 4 | E6: =TEXT(B6,"mmmm") -> April | F6: 44663 | G6: CUST-9047 | H6: Rahul Iyer | I6: Consumer | J6: India | K6: Washington | L6: Spokane | M6: West | N6: PROD-0024 | O6: Furniture | P6: Office Chairs | Q6: Herman Miller Aeron | R6: 2092.5 | S6: 2 | T6: 0.25 | U6: =IF(T6=0,"No Discount",IF(T6<=0.1,"Low",IF(T6<=0.2,"Medium","High"))) -> High | V6: 404.48 | W6: =V6/R6 -> 0.19329988 | X6: 46.75 | Y6: Credit Card | Z6: =IF(R6<500,"Small",IF(R6<=2000,"Medium","Large")) -> Large
A7: ORD-10101 | B7: 45635 | C7: =YEAR(B7) -> 2024 | D7: =MONTH(B7) -> 12 | E7: =TEXT(B7,"mmmm") -> December | F7: 45638 | G7: CUST-5114 | H7: Sneha Gupta | I7: Consumer | J7: India | K7: Arkansas | L7: Little Rock | M7: South | N7: PROD-0013 | O7: Electronics | P7: Accessories | Q7: Anker 65W Charger | R7: 78.4 | S7: 2 | T7: 0.2 | U7: =IF(T7=0,"No Discount",IF(T7<=0.1,"Low",IF(T7<=0.2,"Medium","High"))) -> Medium | V7: 3.74 | W7: =V7/R7 -> 0.047704082 | X7: 39.81 | Y7: UPI | Z7: =IF(R7<500,"Small",IF(R7<=2000,"Medium","Large")) -> Small
A8: ORD-10353 | B8: 44112 | C8: =YEAR(B8) -> 2020 | D8: =MONTH(B8) -> 10 | E8: =TEXT(B8,"mmmm") -> October | F8: 44114 | G8: CUST-3068 | H8: Liang Iyer | I8: Corporate | J8: India | K8: Idaho | L8: Meridian | M8: West | N8: PROD-0042 | O8: Furniture | P8: Beds | Q8: Saatva Classic Mattress | R8: 3220.5 | S8: 2 | T8: 0.05 | U8: =IF(T8=0,"No Discount",IF(T8<=0.1,"Low",IF(T8<=0.2,"Medium","High"))) -> Low | V8: 481.14 | W8: =V8/R8 -> 0.14939916 | X8: 6.45 | Y8: EMI | Z8: =IF(R8<500,"Small",IF(R8<=2000,"Medium","Large")) -> Large
A9: ORD-10571 | B9: 45568 | C9: =YEAR(B9) -> 2024 | D9: =MONTH(B9) -> 10 | E9: =TEXT(B9,"mmmm") -> October | F9: 45572 | G9: CUST-5557 | H9: Aarav Smith | I9: Consumer | J9: United States | K9: Oklahoma | L9: Tulsa | M9: South | N9: PROD-0019 | O9: Electronics | P9: Tablets | Q9: Lenovo Tab P12 | R9: 1396.5 | S9: 5 | T9: 0.3 | U9: =IF(T9=0,"No Discount",IF(T9<=0.1,"Low",IF(T9<=0.2,"Medium","High"))) -> High | V9: 194.49 | W9: =V9/R9 -> 0.1392696 | X9: 49.96 | Y9: Wallet | Z9: =IF(R9<500,"Small",IF(R9<=2000,"Medium","Large")) -> Medium | AJ9: =PROPER(AI9)
A10: ORD-10464 | B10: 44801 | C10: =YEAR(B10) -> 2022 | D10: =MONTH(B10) -> 8 | E10: =TEXT(B10,"mmmm") -> August | F10: 44804 | G10: CUST-8994 | H10: Fang Reddy | I10: Home Office | J10: India | K10: Pennsylvania | L10: Harrisburg | M10: East | N10: PROD-0045 | O10: Furniture | P10: Storage | Q10: IKEA ALEX Drawer Unit | R10: 597 | S10: 4 | T10: 0.25 | U10: =IF(T10=0,"No Discount",IF(T10<=0.1,"Low",IF(T10<=0.2,"Medium","High"))) -> High | V10: 78.09 | W10: =V10/R10 -> 0.13080402 | X10: 38.2 | Y10: EMI | Z10: =IF(R10<500,"Small",IF(R10<=2000,"Medium","Large")) -> Medium | AJ10: =PROPER(AI10)
A11: ORD-10351 | B11: 43884 | C11: =YEAR(B11) -> 2020 | D11: =MONTH(B11) -> 2 | E11: =TEXT(B11,"mmmm") -> February | F11: 43891 | G11: CUST-1420 | H11: Lakshmi Ramirez | I11: Consumer | J11: United States | K11: Kentucky | L11: Bowling Green | M11: South | N11: PROD-0007 | O11: Electronics | P11: Laptops | Q11: HP Spectre x360 | R11: 5395.5 | S11: 5 | T11: 0.1 | U11: =IF(T11=0,"No Discount",IF(T11<=0.1,"Low",IF(T11<=0.2,"Medium","High"))) -> Low | V11: 1177.34 | W11: =V11/R11 -> 0.21820777 | X11: 32.25 | Y11: Net Banking | Z11: =IF(R11<500,"Small",IF(R11<=2000,"Medium","Large")) -> Large | AJ11: =PROPER(AI11)
A12: ORD-10342 | B12: 45601 | C12: =YEAR(B12) -> 2024 | D12: =MONTH(B12) -> 11 | E12: =TEXT(B12,"mmmm") -> November | F12: 45602 | G12: CUST-6062 | H12: Emily Liu | I12: Home Office | J12: United States | K12: Massachusetts | L12: Boston | M12: East | N12: PROD-0060 | O12: Clothing | P12: Kids' Clothing | Q12: Nike Kids Sneakers | R12: 58.5 | S12: 1 | T12: 0.1 | U12: =IF(T12=0,"No Discount",IF(T12<=0.1,"Low",IF(T12<=0.2,"Medium","High"))) -> Low | V12: -17.89 | W12: =V12/R12 -> -0.30581197 | X12: 44.03 | Y12: Net Banking | Z12: =IF(R12<500,"Small",IF(R12<=2000,"Medium","Large")) -> Small | AJ12: =PROPER(AI12)
A13: ORD-10484 | B13: 44570 | C13: =YEAR(B13) -> 2022 | D13: =MONTH(B13) -> 1 | E13: =TEXT(B13,"mmmm") -> January | F13: 44574 | G13: CUST-9619 | H13: Deepa Singh | I13: Home Office | J13: India | K13: South Carolina | L13: Charleston | M13: South | N13: PROD-0003 | O13: Electronics | P13: Smartphones | Q13: OnePlus 12 | R13: 1947 | S13: 3 | T13: 0 | U13: =IF(T13=0,"No Discount",IF(T13<=0.1,"Low",IF(T13<=0.2,"Medium","High"))) -> No Discount | V13: 228.23 | W13: =V13/R13 -> 0.11722137 | X13: 18.04 | Y13: Debit Card | Z13: =IF(R13<500,"Small",IF(R13<=2000,"Medium","Large")) -> Medium | AJ13: =PROPER(AI13)
A14: ORD-10244 | B14: 45188 | C14: =YEAR(B14) -> 2023 | D14: =MONTH(B14) -> 9 | E14: =TEXT(B14,"mmmm") -> September | F14: 45190 | G14: CUST-8957 | H14: Takeshi Watanabe | I14: Home Office | J14: United States | K14: Arkansas | L14: Little Rock | M14: South | N14: PROD-0044 | O14: Furniture | P14: Storage | Q14: IKEA KALLAX Shelf | R14: 745 | S14: 5 | T14: 0 | U14: =IF(T14=0,"No Discount",IF(T14<=0.1,"Low",IF(T14<=0.2,"Medium","High"))) -> No Discount | V14: 137.28 | W14: =V14/R14 -> 0.18426846 | X14: 39.07 | Y14: Wallet | Z14: =IF(R14<500,"Small",IF(R14<=2000,"Medium","Large")) -> Medium
A15: ORD-10503 | B15: 44878 | C15: =YEAR(B15) -> 2022 | D15: =MONTH(B15) -> 11 | E15: =TEXT(B15,"mmmm") -> November | F15: 44881 | G15: CUST-1436 | H15: Chris Kumar | I15: Consumer | J15: India | K15: West Virginia | L15: Huntington | M15: South | N15: PROD-0066 | O15: Clothing | P15: Sportswear | Q15: Champion Hoodie | R15: 82.5 | S15: 2 | T15: 0.25 | U15: =IF(T15=0,"No Discount",IF(T15<=0.1,"Low",IF(T15<=0.2,"Medium","High"))) -> High | V15: 17.67 | W15: =V15/R15 -> 0.21418182 | X15: 9.86 | Y15: Wallet | Z15: =IF(R15<500,"Small",IF(R15<=2000,"Medium","Large")) -> Small
A16: ORD-10390 | B16: 44359 | C16: =YEAR(B16) -> 2021 | D16: =MONTH(B16) -> 6 | E16: =TEXT(B16,"mmmm") -> June | F16: 44362 | G16: CUST-5978 | H16: Ananya Garcia | I16: Home Office | J16: United States | K16: Florida | L16: Jacksonville | M16: East | N16: PROD-0010 | O16: Electronics | P16: Laptops | Q16: Asus ZenBook 14 | R16: 3396 | S16: 4 | T16: 0 | U16: =IF(T16=0,"No Discount",IF(T16<=0.1,"Low",IF(T16<=0.2,"Medium","High"))) -> No Discount | V16: -180.74 | W16: =V16/R16 -> -0.053221437 | X16: 0 | Y16: Cash on Delivery | Z16: =IF(R16<500,"Small",IF(R16<=2000,"Medium","Large")) -> Large
A17: ORD-10642 | B17: 44251 | C17: =YEAR(B17) -> 2021 | D17: =MONTH(B17) -> 2 | E17: =TEXT(B17,"mmmm") -> February | F17: 44255 | G17: CUST-3847 | H17: Yuki Singh | I17: Corporate | J17: India | K17: California | L17: Sacramento | M17: West | N17: PROD-0037 | O17: Furniture | P17: Sofas | Q17: Wayfair Andover Mills Sofa | R17: 1098 | S17: 2 | T17: 0 | U17: =IF(T17=0,"No Discount",IF(T17<=0.1,"Low",IF(T17<=0.2,"Medium","High"))) -> No Discount | V17: 191.24 | W17: =V17/R17 -> 0.17417122 | X17: 21.33 | Y17: Cash on Delivery | Z17: =IF(R17<500,"Small",IF(R17<=2000,"Medium","Large")) -> Medium
A18: ORD-10443 | B18: 43939 | C18: =YEAR(B18) -> 2020 | D18: =MONTH(B18) -> 4 | E18: =TEXT(B18,"mmmm") -> April | F18: 43941 | G18: CUST-8355 | H18: Aditya Hernandez | I18: Consumer | J18: United States | K18: Nevada | L18: Reno | M18: West | N18: PROD-0055 | O18: Clothing | P18: Women's Apparel | Q18: Nike Air Max 270 | R18: 149 | S18: 1 | T18: 0 | U18: =IF(T18=0,"No Discount",IF(T18<=0.1,"Low",IF(T18<=0.2,"Medium","High"))) -> No Discount | V18: 4.15 | W18: =V18/R18 -> 0.027852349 | X18: 35.84 | Y18: Wallet | Z18: =IF(R18<500,"Small",IF(R18<=2000,"Medium","Large")) -> Small
A19: ORD-10949 | B19: 45566 | C19: =YEAR(B19) -> 2024 | D19: =MONTH(B19) -> 10 | E19: =TEXT(B19,"mmmm") -> October | F19: 45568 | G19: CUST-5901 | H19: Carlos Suzuki | I19: Consumer | J19: United States | K19: Minnesota | L19: St. Paul | M19: Central | N19: PROD-0060 | O19: Clothing | P19: Kids' Clothing | Q19: Nike Kids Sneakers | R19: 195 | S19: 4 | T19: 0.25 | U19: =IF(T19=0,"No Discount",IF(T19<=0.1,"Low",IF(T19<=0.2,"Medium","High"))) -> High | V19: 27.52 | W19: =V19/R19 -> 0.14112821 | X19: 5.78 | Y19: Wallet | Z19: =IF(R19<500,"Small",IF(R19<=2000,"Medium","Large")) -> Small
A20: ORD-10748 | B20: 45603 | C20: =YEAR(B20) -> 2024 | D20: =MONTH(B20) -> 11 | E20: =TEXT(B20,"mmmm") -> November | F20: 45606 | G20: CUST-5669 | H20: Arjun Watanabe | I20: Home Office | J20: United States | K20: Kansas | L20: Kansas City | M20: Central | N20: PROD-0062 | O20: Clothing | P20: Kids' Clothing | Q20: Columbia Kids Jacket | R20: 355.5 | S20: 5 | T20: 0.1 | U20: =IF(T20=0,"No Discount",IF(T20<=0.1,"Low",IF(T20<=0.2,"Medium","High"))) -> Low | V20: 43.62 | W20: =V20/R20 -> 0.12270042 | X20: 32.34 | Y20: UPI | Z20: =IF(R20<500,"Small",IF(R20<=2000,"Medium","Large")) -> Small
A21: ORD-10357 | B21: 44427 | C21: =YEAR(B21) -> 2021 | D21: =MONTH(B21) -> 8 | E21: =TEXT(B21,"mmmm") -> August | F21: 44431 | G21: CUST-5843 | H21: Lakshmi Watanabe | I21: Corporate | J21: United States | K21: Mississippi | L21: Hattiesburg | M21: South | N21: PROD-0049 | O21: Clothing | P21: Men's Apparel | Q21: Nike Dri-FIT T-Shirt | R21: 126 | S21: 4 | T21: 0.1 | U21: =IF(T21=0,"No Discount",IF(T21<=0.1,"Low",IF(T21<=0.2,"Medium","High"))) -> Low | V21: 19.55 | W21: =V21/R21 -> 0.15515873 | X21: 39.82 | Y21: Wallet | Z21: =IF(R21<500,"Small",IF(R21<=2000,"Medium","Large")) -> Small
A22: ORD-10947 | B22: 45468 | C22: =YEAR(B22) -> 2024 | D22: =MONTH(B22) -> 6 | E22: =TEXT(B22,"mmmm") -> June | F22: 45474 | G22: CUST-4404 | H22: Carlos Brown | I22: Consumer | J22: United States | K22: Illinois | L22: Chicago | M22: Central | N22: PROD-0003 | O22: Electronics | P22: Smartphones | Q22: OnePlus 12 | R22: 1947 | S22: 3 | T22: 0 | U22: =IF(T22=0,"No Discount",IF(T22<=0.1,"Low",IF(T22<=0.2,"Medium","High"))) -> No Discount | V22: 218.65 | W22: =V22/R22 -> 0.11230098 | X22: 49.95 | Y22: EMI | Z22: =IF(R22<500,"Small",IF(R22<=2000,"Medium","Large")) -> Medium
A23: ORD-10380 | B23: 44597 | C23: =YEAR(B23) -> 2022 | D23: =MONTH(B23) -> 2 | E23: =TEXT(B23,"mmmm") -> February | F23: 44604 | G23: CUST-4866 | H23: Valentina Zhang | I23: Consumer | J23: United States | K23: Wisconsin | L23: Green Bay | M23: Central | N23: PROD-0029 | O23: Furniture | P23: Desks | Q23: IKEA BEKANT Standing Desk | R23: 426.55 | S23: 1 | T23: 0.05 | U23: =IF(T23=0,"No Discount",IF(T23<=0.1,"Low",IF(T23<=0.2,"Medium","High"))) -> Low | V23: 28.83 | W23: =V23/R23 -> 0.067588794 | X23: 46.1 | Y23: Credit Card | Z23: =IF(R23<500,"Small",IF(R23<=2000,"Medium","Large")) -> Small
A24: ORD-10744 | B24: 45294 | C24: =YEAR(B24) -> 2024 | D24: =MONTH(B24) -> 1 | E24: =TEXT(B24,"mmmm") -> January | F24: 45297 | G24: CUST-8260 | H24: Yuki Nair | I24: Consumer | J24: India | K24: Florida | L24: Miami | M24: East | N24: PROD-0059 | O24: Clothing | P24: Kids' Clothing | Q24: Gap Kids T-Shirt Pack | R24: 122.5 | S24: 5 | T24: 0.3 | U24: =IF(T24=0,"No Discount",IF(T24<=0.1,"Low",IF(T24<=0.2,"Medium","High"))) -> High | V24: -19.47 | W24: =V24/R24 -> -0.15893878 | X24: 32.22 | Y24: UPI | Z24: =IF(R24<500,"Small",IF(R24<=2000,"Medium","Large")) -> Small
A25: ORD-10393 | B25: 44677 | C25: =YEAR(B25) -> 2022 | D25: =MONTH(B25) -> 4 | E25: =TEXT(B25,"mmmm") -> April | F25: 44679 | G25: CUST-2929 | H25: Sanjay Miller | I25: Corporate | J25: United States | K25: Tennessee | L25: Knoxville | M25: South | N25: PROD-0043 | O25: Furniture | P25: Beds | Q25: Purple Mattress | R25: 6170.25 | S25: 5 | T25: 0.05 | U25: =IF(T25=0,"No Discount",IF(T25<=0.1,"Low",IF(T25<=0.2,"Medium","High"))) -> Low | V25: 608.13 | W25: =V25/R25 -> 0.098558405 | X25: 29.66 | Y25: PayPal | Z25: =IF(R25<500,"Small",IF(R25<=2000,"Medium","Large")) -> Large
... A1051: ORD-10265 | B1051: 44590 | C1051: =YEAR(B1051) -> 2022 | D1051: =MONTH(B1051) -> 1 | E1051: =TEXT(B1051,"mmmm") -> January | F1051: 44591 | G1051: CUST-7484 | H1051: Suresh Taylor | I1051: Consumer | J1051: United States | K1051: Oklahoma | L1051: Oklahoma City | M1051: South | N1051: PROD-0012 | O1051: Electronics | P1051: Accessories | Q1051: JBL Charge 5 Speaker | R1051: 895 | S1051: 5 | T1051: 0 | U1051: =IF(T1051=0,"No Discount",IF(T1051<=0.1,"Low",IF(T1051<=0.2,"Medium","High"))) -> No Discount | V1051: -82.88 | W1051: =V1051/R1051 -> -0.092603352 | X1051: 37.6 | Y1051: EMI | Z1051: =IF(R1051<500,"Small",IF(R1051<=2000,"Medium","Large")) -> Medium

Sheet Analysis
A1: KPI Values:
H2: Sales By Region | K2: Profit By Category
A3: Total Sales | B3: =SUM(Cleaned_Data!$R$2:$R$1051) -> 1299184.1 | E3: Category | F3: Sum of Sales | H3: Region | I3: Sum of Sales | K3: Category | L3: Sum of Profit | N3: Payment_Method | O3: Count of Order_ID | Q3: Segment | R3: Sum of Sales | U3: Order_Year | V3: Sum of Sales | X3: Order_Year | Y3: Sum of Profit | AA3: Order_Month | AB3: Sum of Sales | AD3: Order_Size | AE3: Count of Order_ID
A4: Profits | B4: =SUM(Cleaned_Data!$V$2:$V$1051) -> 152783.3 | E4: Furniture | F4: 672504.7 | H4: Central | I4: 386682.7 | K4: Furniture | L4: 80616.29 | N4: Debit Card | O4: 141 | Q4: Corporate | R4: 466807.6 | U4: 2024 | V4: 305861.9 | X4: 2024 | Y4: 36162.8 | AA4: October | AB4: 145740.45 | AD4: Large | AE4: 0.22761905
A5: Total Orders | B5: =COUNTA(Cleaned_Data!$A$2:$A$1051) -> 1050 | E5: Electronics | F5: 549586.25 | H5: South | I5: 335343.75 | K5: Electronics | L5: 66372.1 | N5: EMI | O5: 137 | Q5: Consumer | R5: 446090.75 | U5: 2022 | V5: 270474.85 | X5: 2022 | Y5: 35084.72 | AA5: April | AB5: 122712.15 | AD5: Medium | AE5: 0.33047619 | AH5: Monthly Sales Trend | AK5: Top 10 Products By Sales | AN5: Top 10 Customers By Revenue | AQ5: Sales vs Profit Analysis
A6: Quantity Sold | B6: =SUM(Cleaned_Data!$S$2:$S$1051) -> 3054 | E6: Clothing | F6: 77093.15 | H6: East | I6: 294541.75 | K6: Clothing | L6: 5794.91 | N6: Net Banking | O6: 134 | Q6: Home Office | R6: 386285.75 | U6: 2020 | V6: 269233.6 | X6: 2020 | Y6: 31986.27 | AA6: August | AB6: 120664.6 | AD6: Small | AE6: 0.44190476 | AH6: Order_Month | AI6: Sum of Sales | AK6: Product_Name | AL6: Sum of Sales | AN6: Customer_Name | AO6: Sum of Sales | AQ6: Category | AR6: Sum of Profit | AS6: Sum of Sales | AT6: Margin%
A7: Avg Order Value | B7: =AVERAGE(Cleaned_Data!$R$2:$R$1051) -> 1237.3182 | C7: {=SUM(Cleaned_Data!$R$2:$R$1051/COUNTA(Cleaned_Data!$A$2:$A$1051))} -> 1237.3182 | E7: Grand Total | F7: 1299184.1 | H7: West | I7: 282615.9 | K7: Grand Total | L7: 152783.3 | N7: Wallet | O7: 133 | Q7: Grand Total | R7: 1299184.1 | U7: 2023 | V7: 231057.45 | X7: 2021 | Y7: 25514.08 | AA7: May | AB7: 118114.85 | AD7: Grand Total | AE7: 1 | AH7: January | AI7: 104978.9 | AK7: Saatva Classic Mattress | AL7: 83733 | AN7: Lakshmi Ramirez | AO7: 20179.1 | AQ7: Clothing | AR7: 5794.91 | AS7: 77093.15 | AT7: =GETPIVOTDATA("Sum of Profit",$AQ$6,"Category","Clothing")/GETPIVOTDATA("Sum of Sales",$AQ$6,"Category","Clothing") -> 0.075167638
A8: Average Profit Margin | B8: =AVERAGE(Cleaned_Data!W2:W1051) -> 0.083451412 | H8: Grand Total | I8: 1299184.1 | N8: PayPal | O8: 131 | U8: 2021 | V8: 222556.3 | X8: 2023 | Y8: 24035.43 | AA8: December | AB8: 113241.1 | AH8: February | AI8: 90883.95 | AK8: Pottery Barn Comfort Sofa | AL8: 70795.5 | AN8: Matthew Garcia | AO8: 18706.35 | AQ8: Electronics | AR8: 66372.1 | AS8: 549586.25 | AT8: =GETPIVOTDATA("Sum of Profit",$AQ$6,"Category","Electronics")/GETPIVOTDATA("Sum of Sales",$AQ$6,"Category","Electronics") -> 0.1207674
N9: UPI | O9: 131 | U9: Grand Total | V9: 1299184.1 | X9: Grand Total | Y9: 152783.3 | AA9: June | AB9: 111851.7 | AH9: March | AI9: 87649.1 | AK9: HP Spectre x360 | AL9: 70681.05 | AN9: Hana Flores | AO9: 17842.2 | AQ9: Furniture | AR9: 80616.29 | AS9: 672504.7 | AT9: =GETPIVOTDATA("Sum of Profit",$AQ$6,"Category","Furniture")/GETPIVOTDATA("Sum of Sales",$AQ$6,"Category","Furniture") -> 0.11987469
A10: Earliest Date(first order) | B10: =MIN(Cleaned_Data!$B$2:$B$1051) -> 43831 | N10: Cash on Delivery | O10: 123 | AA10: January | AB10: 104978.9 | AH10: April | AI10: 122712.15 | AK10: Casper Wave Hybrid Mattress | AL10: 69344.5 | AN10: Aiko Garcia | AO10: 17202.55 | AQ10: Grand Total | AR10: 152783.3 | AS10: 1299184.1
A11: Latest Date(last order) | B11: =MAX(Cleaned_Data!$B$2:$B$1051) -> 45656 | N11: Credit Card | O11: 115 | AA11: July | AB11: 97147.65 | AH11: May | AI11: 118114.85 | AK11: Steelcase Leap V2 | AL11: 46880.9 | AN11: Lakshmi Watanabe | AO11: 16770.3
N12: Unknown | O12: 5 | AA12: November | AB12: 94743.95 | AH12: June | AI12: 111851.7 | AK12: Asus ZenBook 14 | AL12: 45251.7 | AN12: Vikram Wang | AO12: 16087.4
N13: Grand Total | O13: 1050 | AA13: September | AB13: 91455.7 | AH13: July | AI13: 97147.65 | AK13: Nikon Z30 | AL13: 44683.2 | AN13: Ana Ramirez | AO13: 15205.95
AA14: February | AB14: 90883.95 | AH14: August | AI14: 120664.6 | AK14: Herman Miller Aeron | AL14: 44012.25 | AN14: Fang Reddy | AO14: 14706
AA15: March | AB15: 87649.1 | AH15: September | AI15: 91455.7 | AK15: Purple Mattress | AL15: 40398.9 | AN15: Aarav Smith | AO15: 14654.45
AA16: Grand Total | AB16: 1299184.1 | AH16: October | AI16: 145740.45 | AK16: West Elm Harmony Sofa | AL16: 34926.7 | AN16: Valentina Torres | AO16: 14343.15
AH17: November | AI17: 94743.95 | AK17: Grand Total | AL17: 550707.7 | AN17: Grand Total | AO17: 165697.45
AH18: December | AI18: 113241.1
AH19: Grand Total | AI19: 1299184.1

Sheet Dashboard_KPI
A1: KPI | B1: Values
A2: Total Sales | B2: =SUM(Cleaned_Data!$R$2:$R$1051) -> 1299184.1
A3: Total Profit | B3: =SUM(Cleaned_Data!$V$2:$V$1051) -> 152783.3
A4: Total Orders | B4: =COUNTA(Cleaned_Data!$A$2:$A$1051) -> 1050
A5: Total Quantity Sold | B5: =SUM(Cleaned_Data!$S$2:$S$1051) -> 3054
A6: Average Order Value | B6: =AVERAGE(Cleaned_Data!$R$2:$R$1051) -> 1237.3182
A7: Overall Profit Margin | B7: {=SUM(Cleaned_Data!V1032:V1051/SUM(Cleaned_Data!R1032:R1051))} -> 0.11573138
A10: Year | B10: Sales | C10: Sales Growth %
A11: 2020 | B11: 269233.6 | C11: N/A
A12: 2021 | B12: 222556.3 | C12: =(B12-B11)/B11 -> -0.17337101
A13: 2022 | B13: 270474.85 | C13: =(B13-B12)/B12 -> 0.21530979
A14: 2023 | B14: 231057.45 | C14: =(B14-B13)/B13 -> -0.14573407
A15: 2024 | B15: 305861.9 | C15: =(B15-B14)/B14 -> 0.32374827

Sheet Dashboard
A1: E-Commerce Sales Performance Dashboard
B5: Total Sales | G5: Total Profit | L5: Total Orders | Q5: Total Quantity sold | V5: Average Order Value | AA5: Overall Profit Margin
B6: =Dashboard_KPI!B2 -> 1299184.1 | G6: =Dashboard_KPI!B3 -> 152783.3 | L6: =Dashboard_KPI!B4 -> 1050 | Q6: =Dashboard_KPI!B5 -> 3054 | V6: =Dashboard_KPI!B6 -> 1237.3182 | AA6: =Dashboard_KPI!B7 -> 0.11573138
B93: • Central region generated the highest sales.
B94: • Furniture is the most profitable category.
B95: • October recorded the highest monthly sales.
B96: • 2024 achieved the highest yearly growth.
B97: • Clothing category needs profitability improvement.
